mcp_server_currency_history/__init__.py
mcp_server_currency_history/server.py
mcp_server_currency_history-0.1.1.dist-info/METADATA
mcp_server_currency_history-0.1.1.dist-info/WHEEL
mcp_server_currency_history-0.1.1.dist-info/entry_points.txt
mcp_server_currency_history-0.1.1.dist-info/RECORD
