Metadata-Version: 2.4
Name: mcp-server-currency-history
Version: 0.1.1
Summary: A Model Context Protocol (MCP) server for fetching historical currency exchange rates using the Frankfurter API.
Project-URL: Homepage, https://github.com/example/mcp-server-currency-history
Author-email: User <user@example.com>
License-Expression: MIT
Keywords: currency,exchange-rates,frankfurter,history,mcp
Requires-Python: >=3.10
Requires-Dist: fastmcp
Requires-Dist: httpx
